rds_cp-0.1.2.dist-info/entry_points.txt
rds_cp-0.1.2.dist-info/WHEEL
rds_cp-0.1.2.dist-info/METADATA
rds_cp-0.1.2.dist-info/top_level.txt
rds_cp-0.1.2.dist-info/RECORD
rds_cp-0.1.2.dist-info/DESCRIPTION.rst
rds_cp-0.1.2.dist-info/metadata.json
rds_cp/version.py
rds_cp/rds_cp.py
rds_cp/__init__.py
