Metadata-Version: 2.0
Name: rds-cp
Version: 0.1.2
Summary: cp for RDS instances
Home-page: UNKNOWN
Author: Counsyl Platform Team
Author-email: opensource@counsyl.com
License: UNKNOWN
Platform: UNKNOWN
Classifier: Development Status :: 4 - Beta
Classifier: Environment :: Console
Classifier: Intended Audience :: Developers
Classifier: License :: OSI Approved :: Apache Software License
Classifier: Operating System :: OS Independent
Classifier: Topic :: Database
Classifier: Topic :: Software Development
Classifier: Topic :: System :: Systems Administration
Classifier: Programming Language :: Python :: 3
Classifier: Programming Language :: Python :: 3.4
Classifier: Programming Language :: Python :: 3.5
Classifier: Programming Language :: Python :: 3 :: Only
Requires-Dist: boto3 (==1.1.1)
Requires-Dist: docopt
